ml_dataset_contract/__init__.py
ml_dataset_contract/runtime/__init__.py
ml_dataset_contract/runtime/base_factory.py
ml_dataset_contract/runtime/encoders.py
ml_dataset_contract/runtime/feature_factory.py
ml_dataset_contract/runtime/raw_factory.py
ml_dataset_contract/runtime/request_factory.py
ml_dataset_contract/runtime/schema.py
ml_dataset_contract/runtime/target_factory.py
ml_dataset_contract_core-0.2.0.dist-info/METADATA
ml_dataset_contract_core-0.2.0.dist-info/WHEEL
ml_dataset_contract_core-0.2.0.dist-info/top_level.txt
ml_dataset_contract_core-0.2.0.dist-info/RECORD
