Metadata-Version: 2.4
Name: ml_dataset_contract_core
Version: 0.2.0
Summary: Runtime utilities for ML dataset contract packages
Home-page: https://github.com/nikolskydn/ml_dataset_contract_core
Author: Nikolskii D.N.
Author-email: "Nikolskii D.N." <nikolskydn@mail.ru>
License: MIT
Requires-Python: >=3.10
Requires-Dist: pydantic>=2.6
Requires-Dist: pyyaml>=6.0
Dynamic: author
Dynamic: home-page
Dynamic: requires-python
